imageextras/__init__.py
imageextras/compiled/__init__.py
imageextras/compiled/py310/__init__.py
imageextras/compiled/py310/linux/__init__.py
imageextras/compiled/py310/linux/dithering.cpython-310-x86_64-linux-gnu.so
imageextras/compiled/py310/win/__init__.py
imageextras/compiled/py310/win/dithering.cp310-win_amd64.pyd
imageextras/compiled/py39/__init__.py
imageextras/compiled/py39/linux/__init__.py
imageextras/compiled/py39/linux/dithering.cpython-39-x86_64-linux-gnu.so
imageextras/compiled/py39/win/__init__.py
imageextras/compiled/py39/win/dithering.cp39-win_amd64.pyd
imageextras/src/__init__.py
imageextras/src/utils.py
ImageExtras-0.1.6.dev0.dist-info/LICENSE
ImageExtras-0.1.6.dev0.dist-info/METADATA
ImageExtras-0.1.6.dev0.dist-info/WHEEL
ImageExtras-0.1.6.dev0.dist-info/top_level.txt
ImageExtras-0.1.6.dev0.dist-info/zip-safe
ImageExtras-0.1.6.dev0.dist-info/RECORD
